<?xml version='1.0' encoding='utf-8'?>
<!-- FreeCAD DocumentObject -->
<Document SchemaVersion="4" FileVersion="2">
<Object name="Chamfer001">
  <Properties Count="21" TransientCount="2">
    <_Property name="_Body" type="App::PropertyLinkHidden" status="251658241"/>
    <_Property name="_ElementMapVersion" type="App::PropertyString" status="234881024"/>
    <Property name="AddSubShape" type="Part::PropertyPartShape" status="128">
      <Part ElementMap="0.15.70200.4" brep="1">
<![CDATA[

CASCADE Topology V1, (c) Matra-Datavision
Locations 0
Curve2ds 0
Curves 0
Polygon3D 0
PolygonOnTriangulations 0
Surfaces 0
Triangulations 0

TShapes 0

*]]>
      </Part>
      <ElementMap/>
    </Property>
    <Property name="Angle" type="App::PropertyAngle" status="4">
      <Float value="45"/>
    </Property>
    <Property name="Base" type="App::PropertyLinkSub">
      <LinkSub value="Pad004" count="4">
        <Sub value="Edge7" shadow=";#31d0;:U;XTR;:H3f4:7,E;:H-3f6,E.Edge7"/>
        <Sub value="Edge10" shadow=";#31d1;:U;XTR;:H3f4:7,E;:H-3f6,E.Edge10"/>
        <Sub value="Edge4" shadow=";#31cf;:U;XTR;:H3f4:7,E;:H-3f6,E.Edge4"/>
        <Sub value="Edge12" shadow=";#31d2;:U;XTR;:H3f4:7,E;:H-3f6,E.Edge12"/>
      </LinkSub>
    </Property>
    <Property name="BaseFeature" type="App::PropertyLink" status="8">
      <Link value="Pad004"/>
    </Property>
    <Property name="ChamferType" type="App::PropertyEnumeration">
      <Integer value="0"/>
    </Property>
    <Property name="ColoredElements" type="App::PropertyLinkSubHidden" status="218103808">
      <LinkSub value="" count="0">
      </LinkSub>
    </Property>
    <Property name="ExpressionEngine" type="App::PropertyExpressionEngine" status="67108864">
      <ExpressionEngine count="0"></ExpressionEngine>
    </Property>
    <Property name="FlipDirection" type="App::PropertyBool">
      <Bool value="false"/>
    </Property>
    <Property name="Label" type="App::PropertyString" status="134217728">
      <String value="Chamfer001"/>
    </Property>
    <Property name="Label2" type="App::PropertyString" status="128">
      <String value=""/>
    </Property>
    <Property name="NewSolid" type="App::PropertyBool">
      <Bool value="false"/>
    </Property>
    <Property name="Placement" type="App::PropertyPlacement" status="8388620">
      <PropertyPlacement Px="0" Py="0" Pz="0" Q0="0" Q1="0" Q2="0" Q3="1" A="0" Ox="0" Oy="0" Oz="1"/>
    </Property>
    <Property name="Refine" type="App::PropertyBool">
      <Bool value="true"/>
    </Property>
    <Property name="Shape" type="Part::PropertyPartShape">
      <Part HasherIndex="0" ElementMap="1.15.70200.4" brep="1">
<![CDATA[

CASCADE Topology V1, (c) Matra-Datavision
Locations 13
1
              1               0               0               0 
              0               1               0               0 
              0               0               1               0 
1
              1               0               0               0 
              0               1               0               0 
              0               0               1               0 
2  2 -1 0
1
              1               0               0               0 
              0               1               0               0 
              0               0               1               0 
1
              1               0               0               0 
              0               1               0               0 
              0               0               1               0 
1
              1               0               0               0 
              0               1               0               0 
              0               0               1               0 
2  4 1 5 1 6 -1 0
2  4 1 5 1 6 -1 2 1 0
1
              1               0               0               0 
              0               1               0               0 
              0               0               1               1 
2  6 -1 9 1 2 1 0
2  6 -1 2 1 0
2  4 1 5 1 0
2  2 -1 9 -1 6 1 0
Curve2ds 24
1 0 -0.14142135623730923 1 0 
1 0 -0.80000000000000004 1 0 
1 0 -0.14142135623730923 1 0 
1 0 -0.80000000000000004 1 0 
1 2.4000000000000012 3.2526911934581197 0.57735026918962606 0.81649658092772592 
1 11.599999999999998 3.2526911934581193 -0.57735026918962606 0.81649658092772592 
1 0 0.14142135623731011 1 0 
1 -7 6.7999999999999998 1 0 
1 2.4000000000000012 3.2526911934581197 0.57735026918962606 0.81649658092772592 
1 11.599999999999998 3.2526911934581193 -0.57735026918962606 0.81649658092772592 
1 0 -0.14142135623730923 1 0 
1 0 -0.80000000000000004 1 0 
1 0 -0.14142135623730923 1 0 
1 0 -0.80000000000000004 1 0 
1 11.599999999999998 3.2526911934581193 -0.57735026918962606 0.81649658092772592 
1 2.4000000000000012 3.2526911934581197 0.57735026918962606 0.81649658092772592 
1 0 0.14142135623731011 1 0 
1 -6.7999999999999998 -7 0 1 
1 0 0.14142135623731011 1 0 
1 6.7999999999999998 7 0 -1 
1 0 0.14142135623731011 1 0 
1 7 -6.7999999999999998 -1 0 
1 11.599999999999998 3.2526911934581193 -0.57735026918962606 0.81649658092772592 
1 2.4000000000000012 3.2526911934581197 0.57735026918962606 0.81649658092772592 
Curves 20
1 -7 7 0 0 0 1 
1 -7 7 0.80000000000000004 1 0 0 
1 -7 7 0 1 0 0 
1 7 7 0 0 0 1 
1 -7 -7 0 0 0 1 
1 -7 -7 0.80000000000000004 0 1 0 
1 -7 -7 0 0 1 0 
8 -4.156921938165306 -3.8105117766515315
1 -4.5999999999999988 4.5999999999999979 3.1999999999999993 0.57735026918962606 -0.57735026918962606 0.5773502691896254 
1 -7 6.7999999999999998 1 1 0 0 
8 -4.156921938165306 -3.8105117766515315
1 4.5999999999999979 4.5999999999999988 3.1999999999999993 -0.57735026918962606 -0.57735026918962606 0.5773502691896254 
1 7 7 0 0 -1 0 
1 7 -7 0 -1 0 0 
1 7 7 0.80000000000000004 0 -1 0 
1 7 -7 0 0 0 1 
1 7 -7 0.80000000000000004 -1 0 0 
8 -4.156921938165306 -3.8105117766515315
1 -4.5999999999999979 -4.5999999999999988 3.1999999999999993 0.57735026918962606 0.57735026918962606 0.5773502691896254 
1 -6.7999999999999998 -7 1 0 1 0 
1 6.7999999999999998 7 1 0 -1 0 
1 7 -6.7999999999999998 1 -1 0 0 
8 -4.156921938165306 -3.8105117766515315
1 4.5999999999999988 -4.5999999999999979 3.1999999999999993 -0.57735026918962606 0.57735026918962606 0.5773502691896254 
Polygon3D 0
PolygonOnTriangulations 0
Surfaces 9
1 -7 7 0 0 1 0 1 0 0 0 0 -1 
1 -7 6.9000000000000004 0.90000000000000002 0 0.70710678118654713 0.70710678118654791 1 0 -0 0 -0.70710678118654791 0.70710678118654713 
1 -7 -7 0 -1 0 0 0 1 0 0 0 -1 
1 -6.9000000000000004 -7 0.90000000000000002 -0.70710678118654713 0 0.70710678118654791 0 1 0 0.70710678118654791 -0 0.70710678118654713 
1 0 0 0 0 0 1 1 0 -0 -0 1 0 
1 6.9000000000000004 7 0.90000000000000002 0.70710678118654713 0 0.70710678118654791 0 -1 0 -0.70710678118654791 -0 0.70710678118654713 
1 7 7 0 1 0 -0 0 -1 0 0 -0 -1 
1 7 -7 0 0 -1 0 -1 0 0 -0 -0 -1 
1 7 -6.9000000000000004 0.90000000000000002 0 -0.70710678118654713 0.70710678118654791 -1 0 0 0 0.70710678118654791 0.70710678118654713 
Triangulations 0

TShapes 54
Ve
0.0001
-7 7 0.8
0 0

0101101
*
Ve
1e-07
-7 7 0
0 0

0101101
*
Ed
 1e-07 1 1 0
1  1 0 0 0.8
0

0101000
-54 3 +53 7 *
Ve
0.0001
7 7 0.8
0 0

0101101
*
Ed
 1e-07 1 1 0
1  2 0 0 14
2  1 2 0 0 14
2  2 1 2 0 14
0

0101000
+54 0 -51 0 *
Ve
1e-07
7 7 0
0 0

0101101
*
Ed
 1e-07 1 1 0
1  3 0 0 14
0

0101000
+53 0 -49 0 *
Ed
 1e-07 1 1 0
1  4 0 0 0.8
0

0101000
-51 3 +49 7 *
Wi

0101100
+52 2 +50 0 -48 8 -47 2 *
Fa
0  1e-07 1 0

0101000
+46 3 *
Ve
0.0001
-7 -7 0.8
0 0

0101101
*
Ve
1e-07
-7 -7 0
0 0

0101101
*
Ed
 1e-07 1 1 0
1  5 0 0 0.8
0

0101000
-44 3 +43 7 *
Ed
 1e-07 1 1 0
1  6 0 0 14
2  3 4 0 0 14
2  4 3 2 0 14
0

0101000
+44 0 -54 0 *
Ed
 1e-07 1 1 0
1  7 0 0 14
0

0101000
+43 0 -53 0 *
Wi

0101100
+42 2 +41 0 -40 8 -52 2 *
Fa
0  1e-07 3 0

0101000
+39 3 *
Ve
0.0001
-6.8 6.8 1
0 0

0101101
*
Ed
 1e-07 1 1 0
1  8 0 -4.15692193816531 -3.81051177665153
2  5 2 0 -4.15692193816531 -3.81051177665153
2  6 4 0 -4.15692193816531 -3.81051177665153
0

0101000
+54 0 -37 0 *
Ve
0.0001
6.8 6.8 1
0 0

0101101
*
Ed
 1e-07 1 1 0
1  9 0 0.2 13.8
2  7 2 0 0.2 13.8
2  8 5 10 0.2 13.8
0

0101000
+37 0 -35 0 *
Ed
 1e-07 1 1 0
1  10 0 -4.15692193816531 -3.81051177665153
2  9 6 0 -4.15692193816531 -3.81051177665153
2  10 2 0 -4.15692193816531 -3.81051177665153
0

0101000
+51 0 -35 0 *
Wi

0101100
-36 0 +50 0 -34 0 +33 0 *
Fa
0  0 2 0

0111000
+32 0 *
Ve
1e-07
7 -7 0
0 0

0101101
*
Ed
 1e-07 1 1 0
1  11 0 0 14
0

0101000
+49 0 -30 0 *
Ed
 1e-07 1 1 0
1  12 0 0 14
0

0101000
+30 0 -43 0 *
Wi

0101100
+48 0 +29 0 +28 0 +40 0 *
Fa
0  1e-07 5 0

0101000
-27 12 *
Ve
0.0001
7 -7 0.8
0 0

0101101
*
Ed
 1e-07 1 1 0
1  13 0 0 14
2  11 6 0 0 14
2  12 7 2 0 14
0

0101000
+51 0 -25 0 *
Ed
 1e-07 1 1 0
1  14 0 0 0.8
0

0101000
-25 3 +30 7 *
Wi

0101100
+47 2 +24 0 -29 8 -23 2 *
Fa
0  1e-07 7 0

0101000
+22 3 *
Ed
 1e-07 1 1 0
1  15 0 0 14
2  13 9 0 0 14
2  14 8 2 0 14
0

0101000
+25 0 -44 0 *
Wi

0101100
+23 2 +20 0 -28 8 -42 2 *
Fa
0  1e-07 8 0

0101000
+19 3 *
Ve
0.0001
-6.8 -6.8 1
0 0

0101101
*
Ed
 1e-07 1 1 0
1  16 0 -4.15692193816531 -3.81051177665153
2  15 9 0 -4.15692193816531 -3.81051177665153
2  16 4 0 -4.15692193816531 -3.81051177665153
0

0101000
+44 0 -17 0 *
Ed
 1e-07 1 1 0
1  17 0 0.2 13.8
2  17 4 0 0.2 13.8
2  18 5 10 0.2 13.8
0

0101000
+17 0 -37 0 *
Wi

0101100
-16 0 +41 0 -15 0 +36 0 *
Fa
0  0 4 0

0111000
+14 0 *
Ve
0.0001
6.8 -6.8 1
0 0

0101101
*
Ed
 1e-07 1 1 0
1  18 0 0.2 13.8
2  19 6 0 0.2 13.8
2  20 5 10 0.2 13.8
0

0101000
+35 0 -12 0 *
Ed
 1e-07 1 1 0
1  19 0 0.2 13.8
2  21 9 0 0.2 13.8
2  22 5 10 0.2 13.8
0

0101000
+12 0 -17 0 *
Wi

0101100
-11 0 -34 0 -10 0 -15 0 *
Fa
0  1e-07 5 0

0101000
+9 13 *
Ed
 1e-07 1 1 0
1  20 0 -4.15692193816531 -3.81051177665153
2  23 6 0 -4.15692193816531 -3.81051177665153
2  24 9 0 -4.15692193816531 -3.81051177665153
0

0101000
+25 0 -12 0 *
Wi

0101100
-33 0 +24 0 -11 0 +7 0 *
Fa
0  0 6 0

0111000
+6 0 *
Wi

0101100
-7 0 +20 0 -10 0 +16 0 *
Fa
0  0 9 0

0111000
+4 0 *
Sh

0101100
+45 2 +38 2 -31 0 -26 11 +21 2 +18 2 -13 0 +8 10 -5 0 -3 0 
*
So

0100000
+2 0 *

+1 1 ]]>
      </Part>
      <ElementMap new="1" count="1"><Element key="Dummy" value="Dummy"/></ElementMap>
      <ElementMap2 count="46">
<![CDATA[
25 PostfixCount 14
Edge
Face
Vertex
;:H3f6,V
;:H3f6,E
;:H3f6,F
;:M;CHF;:H3f6:7,E
;:M;CHF;:H3f6:7,F
;:G;CHF;:H3f6:7,F
;:U;CHF;:H3f6:7,E
;:U3;CHF;:H3f6:8,E
;:U4;CHF;:H3f6:8,E
;:U;CHF;:H3f6:7,V
;:U2;CHF;:H3f6:8,V

MapCount 1

ElementMap 1 25 3

Edge

ChildCount 0

NameCount 21
0
$#31ec.7 0
$#31fc.a 0
$#31e5.5 0
$#31ed.7 0
$#31ee.7 0
$#31fd.a 0
$#31e8.5 0
$#31ff.a 0
$#31ff.b 0
$#31ff.c 0
$#31e6.5 0
$#31e7.5 0
$#3200.a 0
$#31ef.7 0
$#3201.a 0
$#3202.a 0
$#3202.b 0
$#3203.a 0
$#3203.b 0
$#3204.c 0

Face

ChildCount 0

NameCount 11
0
$#31f1.8 0
$#31f2.8 0
$#31f4.9 0
$#31ea.6 0
$#31f5.8 0
$#31f6.8 0
$#31f7.9 0
$#31f8.8 0
$#31f9.9 0
$#31fa.9 0

Vertex

ChildCount 0

NameCount 13
0
$#3206.d 0
$#31dc.4 $#31dd.4 0
$#3207.d 0
$#31de.4 $#31df.4 0
$#3208.d 0
$#31e2.4 $#31e3.4 0
$#320a.d 0
$#320a.e 0
$#31e0.4 $#31e1.4 0
$#320b.d 0
$#320c.d 0
$#320d.d 0

EndMap
]]>
      </ElementMap2>
    </Property>
    <Property name="Size" type="App::PropertyQuantityConstraint">
      <Float value="0.2"/>
    </Property>
    <Property name="Size2" type="App::PropertyQuantityConstraint" status="4">
      <Float value="1"/>
    </Property>
    <Property name="SupportTransform" type="App::PropertyBool">
      <Bool value="false"/>
    </Property>
    <Property name="Suppress" type="App::PropertyBool">
      <Bool value="false"/>
    </Property>
    <Property name="SuppressedShape" type="Part::PropertyPartShape">
      <Part ElementMap="0.15.70200.4" brep="1">
<![CDATA[

CASCADE Topology V1, (c) Matra-Datavision
Locations 0
Curve2ds 0
Curves 0
Polygon3D 0
PolygonOnTriangulations 0
Surfaces 0
Triangulations 0

TShapes 0

*]]>
      </Part>
      <ElementMap/>
    </Property>
    <Property name="Visibility" type="App::PropertyBool" status="648">
      <Bool value="true"/>
    </Property>
    <Property name="_Siblings" type="App::PropertyLinkList" status="218103808">
      <LinkList count="0">
      </LinkList>
    </Property>
  </Properties>
</Object>
</Document>
